scepy/__init__.py
scepy/_version.py
scepy/autocorr.py
scepy/batchapply.py
scepy/case_selection.py
scepy/cdc.py
scepy/check_args.py
scepy/combine.py
scepy/corrected_tau.py
scepy/data_processing.py
scepy/data_transformation.py
scepy/describe.py
scepy/dummies_model.py
scepy/formula_utils.py
scepy/hplm.py
scepy/ird.py
scepy/nap.py
scepy/outlier_handling.py
scepy/overlap.py
scepy/pand.py
scepy/prepare_data.py
scepy/rank_transformation.py
scepy/readdata.py
scepy/select_case.py
scepy/singlecasedf.py
scepy/stat_utils.py
scepy/trend.py
scepy/variable_management.py
scepy-0.1.65.dist-info/LICENSE
scepy-0.1.65.dist-info/METADATA
scepy-0.1.65.dist-info/WHEEL
scepy-0.1.65.dist-info/top_level.txt
scepy-0.1.65.dist-info/RECORD
