Metadata-Version: 2.1
Name: scepy
Version: 0.1.65
Summary: Your package description here
Home-page: https://github.com/AhsanKhodami/scepy
Author: Ahsan Khodami
Author-email: ahsan.khodami@gmail.com
Project-URL: Bug Tracker, https://github.com/AhsanKhodami/scepy/issues
Classifier: Programming Language :: Python :: 3
Classifier: License :: OSI Approved :: MIT License
Classifier: Operating System :: OS Independent
Requires-Python: >=3.7
License-File: LICENSE
